{"K":["a","al","ale","alex","alexa","alexan","alexand","alexande","alexander","h","he","hei","heim","heimb","heimbu","heimbuc","heimbuch","t","to","tob","toby","s","st","ste","stef","stefa","stefan","c","ch","chr","chri","chris","christ","christi","christia","christian","r","ra","ral","ralf","ti","tim","si","sim","simo","simon","j","je","jea","jean","jeane","jeanet","jeanett","jeanette","d","da","dan","dani","danie","daniel","daniela","do","dom","domi","domin","domini","dominik","de","den","denn","denni","dennis","se","seb","seba","sebas","sebast","sebasti","sebastia","sebastian","e","ei","ein","eins","einsp","einspi","einspie","einspiel","einspiele","einspieler","an","and","andr","andre","andrea","andreas","m","mi","mic","mich","micha","michae","michael","michaela","l","le","let","lett","letty","er","eri","eric","b","be","ben","leh","lehr","te","teu","teub","teube","teuber","teubert","ba","bai","baie","baier","sc","sch","schu","schul","schulz","bed","bedn","bedna","bednar","bednare","bednarek","sto","stoc","stock","stockm","stockma","stockman","stockmann","p","pr","pri","prit","pritl","pritlo","pritlov","pritlove","i","is","ish","isho","ishor","ishors","ishorst","w","wa","wag","wagn","wagne","wagner","mo","mor","morh","morha","morhar","morhard","morhardt","re","rei","reim","reime","reimer","reimers","hu","hub","hube","hubel","z","zi","zim","zimm","zimme","zimmer","rn","ll","lle","ller","scha","schaa","schaar"],"P":["cef718c6-8213-4339-8011-931cbbcbe870","3d9d13c5-52d4-4ef6-907b-c27814e6a6f8","1d9085a5-7042-412c-88a3-19a98783583d","f6ed02b6-3a82-4106-8cd9-5bb8b07226c5","6625a222-7f40-480c-95e2-c074f6f53d2b","b95e461f-537f-4a6d-9d4b-e652689ab2cb","f94a6611-6ac3-43cb-96cc-e487dbf4a3a9","6f1645dc-e6f1-4a40-a671-eccbcf97bd4d","77a5e82d-32b3-4fdf-8fce-a84afd341bed","9930cf8d-b63b-48fb-bd91-934bd6679e3f","7884e054-361d-40f3-832b-552c51b29532","11250d00-49ed-4c0f-b494-8d0aa798f293","4ab10db1-5ec3-4886-8f4f-002221448e60","5252dce3-edaf-4b71-9733-dea223f69f51","185a8556-a64e-4698-b08f-9f2c186b87eb","16417163-ea0b-408e-9427-36681df81262","c944c1a9-edfb-4a3a-9bcc-b6022e06c696","34ae7bf0-9b10-4a16-ac08-6192e892ab30","6e7302cc-bea2-4a3a-bf78-25176c8523d8","5a9df964-79e4-4f80-a6ea-af3292f22f37","28fd60a4-cc16-4109-8b46-7ab7cb555c82","d96902f4-f012-4369-a2a4-fca304860043","5b72726b-cf23-45f4-897c-a4961624ea62","32ca69b8-d9db-45ae-877e-dc5637cb0d76","8a05d0cd-3d1b-44c4-ab83-d8145c63b066","4e9aad83-2b9b-463f-988d-a5066376c3d2","21ce07de-d577-4664-bf13-af5e592611dc","448860de-a9b8-4f93-b9f3-98475bb276bd","09fb315a-1871-48df-86be-dc93309514a4","4c0cfc8e-62de-43ef-af3a-be7ad21c02fe","820dc8ce-7b95-42e8-b7a4-5e0838cae23b","81fa9e40-556e-4fbe-8693-cdf911b3aad1","1ddf2b23-7c71-4926-af0d-622106a6d0e5","a0e2d323-d322-4f3a-9ba5-1cffc9a7316b","1c50743c-d525-483e-96b6-b4cc624ec405"],"_":[[{"0":["p:0","p:1","p:2","p:3","p:4","p:5","p:6","p:7","p:8","p:9","p:a","p:b","p:c","p:d","p:e","p:f","p:t","p:g"],"1":["p:0","p:1","p:2","p:3","p:4","p:5","p:6","p:7","p:8","p:9","p:a","p:b","p:c","p:d","p:e","p:f","p:g"],"2":["p:0","p:1","p:2","p:3","p:4","p:5","p:6","p:7","p:8","p:9","p:a","p:b","p:c","p:d","p:e","p:f","p:g"],"3":["p:0","p:1","p:2","p:3","p:4","p:5","p:6","p:7","p:8","p:9","p:a","p:b","p:c","p:d","p:e","p:f","p:g"],"4":["p:0","p:1","p:2","p:3","p:4","p:5","p:6","p:7","p:8","p:9","p:a","p:b","p:c","p:d","p:e","p:f","p:g"],"5":["p:0","p:1","p:2","p:3","p:4","p:5","p:6","p:7","p:8","p:9","p:a","p:b","p:c","p:d","p:e","p:f","p:g"],"6":["p:0","p:1","p:2","p:3","p:4","p:5","p:6","p:7","p:8","p:9","p:a","p:b","p:c","p:d","p:e","p:f","p:g"],"7":["p:0","p:1","p:2","p:3","p:4","p:5","p:6","p:7","p:8","p:9","p:a","p:b","p:c","p:d","p:e","p:f","p:g"],"8":["p:0","p:1","p:2","p:3","p:4","p:5","p:6","p:7","p:8","p:9","p:a","p:b","p:c","p:d","p:e","p:f","p:g"],"9":["p:4","p:c","p:e","p:f"],"10":["p:k"],"11":["p:k"],"12":["p:k"],"13":["p:k"],"14":["p:l"],"15":["p:l"],"16":["p:m"],"17":["p:m"],"18":["p:m"],"19":["p:m"],"20":["p:r"],"21":["p:r"],"22":["p:r"],"23":["p:r"],"24":["p:r"],"25":["p:r"],"26":["p:r"],"27":["p:r"],"28":["p:s","p:w"],"29":["p:s"],"30":["p:v"],"31":["p:w"],"32":["p:w"],"33":["p:w"],"34":["p:x"],"35":["p:x"],"36":["p:x"],"a":["p:4","p:c","p:e","p:f"],"b":["p:4","p:c","p:e","p:f"],"c":["p:4","p:c","p:e","p:f"],"d":["p:4","p:c","p:e","p:f"],"e":["p:4","p:c","p:e","p:f"],"f":["p:4","p:c","p:e","p:f"],"g":["p:4","p:c","p:e","p:f"],"h":["p:h","p:l"],"i":["p:h"],"j":["p:h"],"k":["p:h"],"l":["p:i","p:m","p:r"],"m":["p:i"],"n":["p:i"],"o":["p:i"],"p":["p:i"],"q":["p:i"],"r":["p:j"],"s":["p:j"],"t":["p:j"],"u":["p:j"],"v":["p:j"],"w":["p:j"],"x":["p:j"],"y":["p:j"],"z":["p:j"],"1a":["p:n","p:y"],"1b":["p:n"],"1c":["p:n"],"1d":["p:n"],"1e":["p:n"],"1f":["p:n"],"1g":["p:n"],"1h":["p:n"],"1i":["p:o","p:p","p:q"],"1j":["p:o"],"1k":["p:o"],"1l":["p:o"],"1m":["p:o"],"1n":["p:o"],"1o":["p:o"],"1p":["p:p"],"1q":["p:p"],"1r":["p:p"],"1s":["p:p"],"1t":["p:p"],"1u":["p:p"],"1v":["p:q"],"1w":["p:q"],"1x":["p:q"],"1y":["p:q"],"1z":["p:q"],"2a":["p:s"],"2b":["p:s"],"2c":["p:s"],"2d":["p:s"],"2e":["p:s"],"2f":["p:s"],"2g":["p:s"],"2h":["p:s"],"2i":["p:t"],"2j":["p:t"],"2k":["p:t"],"2l":["p:t"],"2m":["p:t"],"2n":["p:t"],"2o":["p:u"],"2p":["p:u"],"2q":["p:u"],"2r":["p:u"],"2s":["p:u"],"2t":["p:u"],"2u":["p:u"],"2v":["p:u"],"2w":["p:v"],"2x":["p:v"],"2y":["p:v"],"2z":["p:v"]},{"9":["p:0","p:1","p:2","p:3","p:5","p:6","p:7","p:8","p:9","p:a","p:b","p:d","p:t","p:g"],"10":["p:r","p:y"],"28":["p:2","p:3","p:4","p:6","p:7","p:8","p:9","p:a","p:b","p:c","p:d","p:e","p:f"],"30":["p:4"],"31":["p:2","p:3","p:4","p:6","p:7","p:8","p:9","p:a","p:b","p:c","p:d","p:e","p:f"],"32":["p:2","p:3","p:4","p:6","p:7","p:8","p:9","p:a","p:b","p:c","p:d","p:e","p:f"],"33":["p:2","p:3","p:4","p:6","p:7","p:8","p:9","p:a","p:b","p:c","p:d","p:e","p:f"],"34":["p:h","p:j"],"35":["p:j"],"37":["p:0","p:1","p:2","p:3","p:4","p:5","p:6","p:7","p:8","p:9","p:a","p:b","p:c","p:d","p:e","p:f","p:u"],"38":["p:0","p:1","p:2","p:3","p:4","p:5","p:6","p:7","p:8","p:9","p:a","p:b","p:c","p:d","p:e","p:f","p:u"],"39":["p:4","p:c","p:e","p:f","p:w"],"40":["p:k"],"41":["p:l"],"42":["p:l"],"43":["p:l"],"44":["p:l"],"45":["p:l"],"46":["p:l"],"47":["p:l"],"48":["p:l"],"49":["p:o"],"50":["p:t"],"51":["p:t"],"52":["p:t"],"53":["p:x"],"54":["p:x"],"55":["p:x"],"56":["p:x"],"57":["p:x"],"58":["p:x"],"59":["p:y"],"a":["p:0","p:1","p:2","p:3","p:5","p:6","p:7","p:8","p:9","p:a","p:b","p:d","p:g"],"b":["p:0","p:1","p:2","p:3","p:5","p:6","p:7","p:8","p:9","p:a","p:b","p:d","p:g"],"c":["p:0","p:1","p:2","p:3","p:5","p:6","p:7","p:8","p:9","p:a","p:b","p:d","p:g"],"d":["p:0","p:1","p:2","p:3","p:5","p:6","p:7","p:8","p:9","p:a","p:b","p:d","p:g"],"e":["p:0","p:1","p:2","p:3","p:5","p:6","p:7","p:8","p:9","p:a","p:b","p:d","p:g"],"f":["p:0","p:1","p:2","p:3","p:5","p:6","p:7","p:8","p:9","p:a","p:b","p:d","p:g"],"g":["p:0","p:1","p:2","p:3","p:5","p:6","p:7","p:8","p:9","p:a","p:b","p:d","p:g"],"2o":["p:0","p:1","p:2","p:3","p:4","p:5","p:6","p:7","p:8","p:9","p:a","p:b","p:c","p:d","p:e","p:f","p:n","p:q"],"2p":["p:0","p:1","p:2","p:3","p:4","p:5","p:6","p:7","p:8","p:9","p:a","p:b","p:c","p:d","p:e","p:f"],"2q":["p:0","p:1","p:2","p:3","p:4","p:5","p:6","p:7","p:8","p:9","p:a","p:b","p:c","p:d","p:e","p:f"],"2r":["p:0","p:1","p:2","p:3","p:4","p:5","p:6","p:7","p:8","p:9","p:a","p:b","p:c","p:d","p:e","p:f"],"2s":["p:0","p:1","p:2","p:3","p:4","p:5","p:6","p:7","p:8","p:9","p:a","p:b","p:c","p:d","p:e","p:f"],"2t":["p:0","p:1","p:2","p:3","p:4","p:5","p:6","p:7","p:8","p:9","p:a","p:b","p:c","p:d","p:e","p:f"],"2u":["p:0","p:1","p:2","p:3","p:4","p:5","p:6","p:7","p:8","p:9","p:a","p:b","p:c","p:d","p:e","p:f"],"2v":["p:0","p:1","p:2","p:3","p:4","p:5","p:6","p:7","p:8","p:9","p:a","p:b","p:c","p:d","p:e","p:f"],"2w":["p:0","p:1","p:2","p:3","p:4","p:5","p:6","p:7","p:8","p:9","p:a","p:b","p:c","p:d","p:e","p:f","p:u"],"2x":["p:0","p:1","p:2","p:3","p:4","p:5","p:6","p:7","p:8","p:9","p:a","p:b","p:c","p:d","p:e","p:f","p:u"],"h":["p:4","p:c","p:e","p:f","p:w"],"3a":["p:4","p:c","p:e","p:f","p:w"],"3b":["p:4","p:c","p:e","p:f","p:w"],"3c":["p:4","p:c","p:e","p:f","p:w"],"3d":["p:4","p:c","p:e","p:f","p:w"],"3e":["p:4","p:c","p:e","p:f","p:w"],"2y":["p:4"],"2z":["p:4"],"2i":["p:c"],"2j":["p:c"],"2k":["p:c"],"2l":["p:c"],"2m":["p:c"],"2n":["p:c"],"3f":["p:h"],"3g":["p:h"],"3h":["p:h"],"3i":["p:h"],"3j":["p:i"],"3k":["p:i"],"3l":["p:i"],"3m":["p:i"],"3n":["p:i"],"3o":["p:j"],"3p":["p:j"],"3q":["p:j"],"3r":["p:j"],"3s":["p:j"],"3t":["p:j"],"l":["p:k"],"m":["p:k"],"3u":["p:k"],"3v":["p:k"],"3w":["p:k"],"3x":["p:k"],"3y":["p:k"],"3z":["p:k"],"4a":["p:o"],"4b":["p:o"],"4c":["p:o"],"4d":["p:o"],"4e":["p:o"],"4f":["p:o"],"4g":["p:p"],"4h":["p:p"],"4i":["p:p"],"4j":["p:p"],"4k":["p:p"],"4l":["p:p"],"4m":["p:q"],"4n":["p:q"],"4o":["p:q"],"4p":["p:q"],"4q":["p:q"],"4r":["p:q"],"4s":["p:q"],"4t":["p:r"],"4u":["p:r"],"4v":["p:r"],"4w":["p:r"],"4x":["p:r"],"4y":["p:r"],"4z":["p:t"]},{"10":["p:b","p:d","p:f"],"11":["p:b"],"12":["p:b"],"13":["p:b"],"14":["p:4","p:c"],"15":["p:4","p:c"],"16":["p:2"],"17":["p:2"],"18":["p:2"],"19":["p:2"],"20":["p:d"],"21":["p:d"],"22":["p:d"],"23":["p:d"],"24":["p:d"],"25":["p:d"],"26":["p:d"],"27":["p:d"],"28":["p:0","p:1","p:5"],"29":["p:c"],"31":["p:0","p:1","p:5"],"32":["p:0","p:1","p:5"],"33":["p:0","p:1","p:5"],"34":["p:3","p:8","p:9"],"35":["p:3","p:8"],"36":["p:3"],"39":["p:0","p:1","p:2","p:3","p:5","p:6","p:7","p:8","p:9","p:a","p:b","p:d"],"40":["p:b"],"41":["p:4","p:c"],"42":["p:4","p:c"],"43":["p:4","p:c"],"44":["p:4","p:c"],"45":["p:4","p:c"],"46":["p:4","p:c"],"47":["p:4","p:c"],"48":["p:4","p:c"],"49":["p:6"],"50":["p:c"],"51":["p:c"],"52":["p:c"],"53":["p:3"],"54":["p:3"],"55":["p:3"],"56":["p:3"],"57":["p:3"],"58":["p:3"],"59":["p:f"],"h":["p:0","p:1","p:2","p:3","p:5","p:6","p:7","p:8","p:9","p:a","p:b","p:d"],"3a":["p:0","p:1","p:2","p:3","p:5","p:6","p:7","p:8","p:9","p:a","p:b","p:d"],"3b":["p:0","p:1","p:2","p:3","p:5","p:6","p:7","p:8","p:9","p:a","p:b","p:d"],"3c":["p:0","p:1","p:2","p:3","p:5","p:6","p:7","p:8","p:9","p:a","p:b","p:d"],"3d":["p:0","p:1","p:2","p:3","p:5","p:6","p:7","p:8","p:9","p:a","p:b","p:d"],"3e":["p:0","p:1","p:2","p:3","p:5","p:6","p:7","p:8","p:9","p:a","p:b","p:d"],"l":["p:2","p:7","p:b","p:d","p:f","p:y"],"1i":["p:4","p:6","p:a"],"1p":["p:4"],"1q":["p:4"],"1r":["p:4"],"1s":["p:4"],"1t":["p:4"],"1u":["p:4"],"4g":["p:4"],"4h":["p:4"],"4i":["p:4"],"4j":["p:4"],"4k":["p:4"],"4l":["p:4"],"1j":["p:6"],"1k":["p:6"],"1l":["p:6"],"1m":["p:6"],"1n":["p:6"],"1o":["p:6"],"4a":["p:6"],"4b":["p:6"],"4c":["p:6"],"4d":["p:6"],"4e":["p:6"],"4f":["p:6"],"m":["p:7","p:b"],"n":["p:7"],"o":["p:7"],"p":["p:7"],"q":["p:7"],"3j":["p:7","p:f","p:y"],"3k":["p:7","p:f","p:y"],"3l":["p:7"],"3m":["p:7"],"3n":["p:7"],"r":["p:8"],"s":["p:8"],"t":["p:8"],"u":["p:8"],"v":["p:8"],"w":["p:8"],"x":["p:8"],"y":["p:8"],"z":["p:8"],"3o":["p:8"],"3p":["p:8"],"3q":["p:8"],"3r":["p:8"],"3s":["p:8"],"3t":["p:8"],"i":["p:9"],"j":["p:9"],"k":["p:9"],"3f":["p:9"],"3g":["p:9"],"3h":["p:9"],"3i":["p:9"],"1v":["p:a"],"1w":["p:a"],"1x":["p:a"],"1y":["p:a"],"1z":["p:a"],"4m":["p:a"],"4n":["p:a"],"4o":["p:a"],"4p":["p:a"],"4q":["p:a"],"4r":["p:a"],"4s":["p:a"],"3u":["p:b"],"3v":["p:b"],"3w":["p:b"],"3x":["p:b"],"3y":["p:b"],"3z":["p:b"],"4z":["p:c"],"2a":["p:c"],"2b":["p:c"],"2c":["p:c"],"2d":["p:c"],"2e":["p:c"],"2f":["p:c"],"2g":["p:c"],"2h":["p:c"],"4t":["p:d"],"4u":["p:d"],"4v":["p:d"],"4w":["p:d"],"4x":["p:d"],"4y":["p:d"],"1a":["p:e","p:f"],"1b":["p:e"],"1c":["p:e"],"1d":["p:e"],"1e":["p:e"],"1f":["p:e"],"1g":["p:e"],"1h":["p:e"],"5a":["p:e","p:n"],"5b":["p:e","p:n"],"5c":["p:e","p:n"],"5d":["p:f","p:y"],"5e":["p:f","p:y"],"5f":["p:f","p:y"],"2w":["p:n"]},{},{},{},{},{},{}],{},["@cef718c6-8213-4339-8011-931cbbcbe870","@3d9d13c5-52d4-4ef6-907b-c27814e6a6f8","@1d9085a5-7042-412c-88a3-19a98783583d","@f6ed02b6-3a82-4106-8cd9-5bb8b07226c5","@6625a222-7f40-480c-95e2-c074f6f53d2b","@b95e461f-537f-4a6d-9d4b-e652689ab2cb","@f94a6611-6ac3-43cb-96cc-e487dbf4a3a9","@6f1645dc-e6f1-4a40-a671-eccbcf97bd4d","@77a5e82d-32b3-4fdf-8fce-a84afd341bed","@9930cf8d-b63b-48fb-bd91-934bd6679e3f","@7884e054-361d-40f3-832b-552c51b29532","@11250d00-49ed-4c0f-b494-8d0aa798f293","@4ab10db1-5ec3-4886-8f4f-002221448e60","@5252dce3-edaf-4b71-9733-dea223f69f51","@185a8556-a64e-4698-b08f-9f2c186b87eb","@16417163-ea0b-408e-9427-36681df81262","@34ae7bf0-9b10-4a16-ac08-6192e892ab30","@6e7302cc-bea2-4a3a-bf78-25176c8523d8","@5a9df964-79e4-4f80-a6ea-af3292f22f37","@28fd60a4-cc16-4109-8b46-7ab7cb555c82","@d96902f4-f012-4369-a2a4-fca304860043","@5b72726b-cf23-45f4-897c-a4961624ea62","@32ca69b8-d9db-45ae-877e-dc5637cb0d76","@8a05d0cd-3d1b-44c4-ab83-d8145c63b066","@4e9aad83-2b9b-463f-988d-a5066376c3d2","@21ce07de-d577-4664-bf13-af5e592611dc","@448860de-a9b8-4f93-b9f3-98475bb276bd","@09fb315a-1871-48df-86be-dc93309514a4","@4c0cfc8e-62de-43ef-af3a-be7ad21c02fe","@820dc8ce-7b95-42e8-b7a4-5e0838cae23b","@81fa9e40-556e-4fbe-8693-cdf911b3aad1","@c944c1a9-edfb-4a3a-9bcc-b6022e06c696","@1ddf2b23-7c71-4926-af0d-622106a6d0e5","@a0e2d323-d322-4f3a-9ba5-1cffc9a7316b","@1c50743c-d525-483e-96b6-b4cc624ec405"]]}